MANIFEST.in
README.md
setup.py
./.gitignore
./Dockerfile
./LICENSE
./MANIFEST.in
./Makefile
./README.md
./RIPE Simulations GitHub.ipynb
./VERSION.txt
./requirements.txt
./setup.py
./.git/FETCH_HEAD
./.git/HEAD
./.git/config
./.git/description
./.git/index
./.git/hooks/applypatch-msg.sample
./.git/hooks/commit-msg.sample
./.git/hooks/fsmonitor-watchman.sample
./.git/hooks/post-update.sample
./.git/hooks/pre-applypatch.sample
./.git/hooks/pre-commit.sample
./.git/hooks/pre-merge-commit.sample
./.git/hooks/pre-push.sample
./.git/hooks/pre-rebase.sample
./.git/hooks/pre-receive.sample
./.git/hooks/prepare-commit-msg.sample
./.git/hooks/update.sample
./.git/info/exclude
./.git/logs/HEAD
./.git/logs/refs/heads/master
./.git/logs/refs/remotes/origin/master
./.git/objects/pack/pack-29042dc367fdc4212fdc7995a319133bad49a595.idx
./.git/objects/pack/pack-29042dc367fdc4212fdc7995a319133bad49a595.pack
./.git/refs/heads/master
./.git/refs/remotes/origin/master
./.git/refs/tags/v0.1
./.github/workflows/push.yml
./RIPE/RIPE.py
./RIPE/__init__.py
./ripe_algorithm.egg-info/PKG-INFO
./ripe_algorithm.egg-info/SOURCES.txt
./ripe_algorithm.egg-info/dependency_links.txt
./ripe_algorithm.egg-info/requires.txt
./ripe_algorithm.egg-info/top_level.txt
RIPE/RIPE.py
RIPE/__init__.py
ripe_algorithm.egg-info/PKG-INFO
ripe_algorithm.egg-info/SOURCES.txt
ripe_algorithm.egg-info/dependency_links.txt
ripe_algorithm.egg-info/requires.txt
ripe_algorithm.egg-info/top_level.txt