Metadata-Version: 2.1
Name: ripe-algorithm
Version: 0.1.6
Summary: Ripe algorithm
Home-page: https://github.com/Advestis/RIPE
Author: Vincent MARGOT
Author-email: vincent.margot@hotmail.fr
License: UNKNOWN
Platform: UNKNOWN
Classifier: Programming Language :: Python :: 3
Classifier: License :: OSI Approved :: GNU General Public License v3 (GPLv3)
Classifier: Operating System :: OS Independent
Classifier: Development Status :: 5 - Production/Stable
Requires-Python: >=3.6
